[
  {
    "id": "L1-AN-01",
    "level": 1,
    "topic": "Animals",
    "type": "picture-match",
    "question": "Which word matches this picture?",
    "image": "🐱",
    "options": [
      "le chat",
      "le chien",
      "le lapin",
      "l'oiseau"
    ],
    "answer": "le chat",
    "points": 10,
    "hint": "This animal says meow!"
  },
  {
    "id": "L1-AN-02",
    "level": 1,
    "topic": "Animals",
    "type": "picture-match",
    "question": "Which word matches this picture?",
    "image": "🐶",
    "options": [
      "le cheval",
      "le chien",
      "le poisson",
      "le cochon"
    ],
    "answer": "le chien",
    "points": 10,
    "hint": "This animal says woof!"
  },
  {
    "id": "L1-AN-03",
    "level": 1,
    "topic": "Animals",
    "type": "picture-match",
    "question": "Which word matches this picture?",
    "image": "🐰",
    "options": [
      "le chat",
      "le lapin",
      "la vache",
      "le mouton"
    ],
    "answer": "le lapin",
    "points": 10,
    "hint": "This animal has long ears"
  },
  {
    "id": "L1-AN-04",
    "level": 1,
    "topic": "Animals",
    "type": "picture-match",
    "question": "Which word matches this picture?",
    "image": "🐦",
    "options": [
      "le poisson",
      "le cheval",
      "l'oiseau",
      "le cochon"
    ],
    "answer": "l'oiseau",
    "points": 10,
    "hint": "This animal can fly"
  },
  {
    "id": "L1-AN-05",
    "level": 1,
    "topic": "Animals",
    "type": "multiple-choice",
    "question": "What is 'le cheval' in English?",
    "options": [
      "fish",
      "horse",
      "cow",
      "sheep"
    ],
    "answer": "horse",
    "points": 10
  },
  {
    "id": "L1-AN-06",
    "level": 1,
    "topic": "Animals",
    "type": "multiple-choice",
    "question": "What is 'la vache' in English?",
    "options": [
      "pig",
      "horse",
      "cow",
      "rabbit"
    ],
    "answer": "cow",
    "points": 10
  },
  {
    "id": "L1-AN-07",
    "level": 1,
    "topic": "Animals",
    "type": "picture-match",
    "question": "Which word matches this picture?",
    "image": "🐷",
    "options": [
      "le mouton",
      "le cochon",
      "le lapin",
      "le chien"
    ],
    "answer": "le cochon",
    "points": 10,
    "hint": "This animal says oink!"
  },
  {
    "id": "L1-AN-08",
    "level": 1,
    "topic": "Animals",
    "type": "multiple-choice",
    "question": "How do you say 'fish' in French?",
    "options": [
      "le cheval",
      "l'oiseau",
      "le poisson",
      "le mouton"
    ],
    "answer": "le poisson",
    "points": 10
  },
  {
    "id": "L1-AN-09",
    "level": 1,
    "topic": "Animals",
    "type": "picture-match",
    "question": "Which word matches this picture?",
    "image": "🐑",
    "options": [
      "le mouton",
      "la vache",
      "le cheval",
      "le cochon"
    ],
    "answer": "le mouton",
    "points": 10,
    "hint": "This animal gives us wool"
  },
  {
    "id": "L1-AN-10",
    "level": 1,
    "topic": "Animals",
    "type": "multiple-choice",
    "question": "What is 'le tigre' in English?",
    "options": [
      "lion",
      "tiger",
      "bear",
      "elephant"
    ],
    "answer": "tiger",
    "points": 10
  },
  {
    "id": "L1-CO-01",
    "level": 1,
    "topic": "Colours",
    "type": "picture-match",
    "question": "What colour is this?",
    "image": "🔵",
    "options": [
      "rouge",
      "bleu",
      "vert",
      "jaune"
    ],
    "answer": "bleu",
    "points": 10,
    "hint": "The colour of the sky"
  },
  {
    "id": "L1-CO-02",
    "level": 1,
    "topic": "Colours",
    "type": "picture-match",
    "question": "What colour is this?",
    "image": "🔴",
    "options": [
      "bleu",
      "noir",
      "rouge",
      "orange"
    ],
    "answer": "rouge",
    "points": 10,
    "hint": "The colour of an apple"
  },
  {
    "id": "L1-CO-03",
    "level": 1,
    "topic": "Colours",
    "type": "picture-match",
    "question": "What colour is this?",
    "image": "🟡",
    "options": [
      "vert",
      "jaune",
      "rose",
      "blanc"
    ],
    "answer": "jaune",
    "points": 10,
    "hint": "The colour of the sun"
  },
  {
    "id": "L1-CO-04",
    "level": 1,
    "topic": "Colours",
    "type": "picture-match",
    "question": "What colour is this?",
    "image": "🟢",
    "options": [
      "violet",
      "rouge",
      "bleu",
      "vert"
    ],
    "answer": "vert",
    "points": 10,
    "hint": "The colour of grass"
  },
  {
    "id": "L1-CO-05",
    "level": 1,
    "topic": "Colours",
    "type": "multiple-choice",
    "question": "What is 'noir' in English?",
    "options": [
      "white",
      "grey",
      "black",
      "brown"
    ],
    "answer": "black",
    "points": 10
  },
  {
    "id": "L1-CO-06",
    "level": 1,
    "topic": "Colours",
    "type": "multiple-choice",
    "question": "How do you say 'white' in French?",
    "options": [
      "gris",
      "blanc",
      "beige",
      "rose"
    ],
    "answer": "blanc",
    "points": 10
  },
  {
    "id": "L1-CO-07",
    "level": 1,
    "topic": "Colours",
    "type": "picture-match",
    "question": "What colour is this?",
    "image": "🟠",
    "options": [
      "jaune",
      "rouge",
      "orange",
      "marron"
    ],
    "answer": "orange",
    "points": 10
  },
  {
    "id": "L1-CO-08",
    "level": 1,
    "topic": "Colours",
    "type": "multiple-choice",
    "question": "What is 'rose' in English?",
    "options": [
      "purple",
      "pink",
      "red",
      "orange"
    ],
    "answer": "pink",
    "points": 10
  },
  {
    "id": "L1-CO-09",
    "level": 1,
    "topic": "Colours",
    "type": "multiple-choice",
    "question": "How do you say 'purple' in French?",
    "options": [
      "gris",
      "marron",
      "violet",
      "beige"
    ],
    "answer": "violet",
    "points": 10
  },
  {
    "id": "L1-CO-10",
    "level": 1,
    "topic": "Colours",
    "type": "multiple-choice",
    "question": "What is 'marron' in English?",
    "options": [
      "grey",
      "brown",
      "black",
      "beige"
    ],
    "answer": "brown",
    "points": 10
  },
  {
    "id": "L1-NU-01",
    "level": 1,
    "topic": "Numbers",
    "type": "multiple-choice",
    "question": "What is 'un' in English?",
    "options": [
      "2",
      "1",
      "3",
      "0"
    ],
    "answer": "1",
    "points": 10
  },
  {
    "id": "L1-NU-02",
    "level": 1,
    "topic": "Numbers",
    "type": "picture-match",
    "question": "Which French word matches?",
    "image": "✌️",
    "options": [
      "un",
      "trois",
      "deux",
      "quatre"
    ],
    "answer": "deux",
    "points": 10
  },
  {
    "id": "L1-NU-03",
    "level": 1,
    "topic": "Numbers",
    "type": "multiple-choice",
    "question": "How do you say '3' in French?",
    "options": [
      "deux",
      "quatre",
      "cinq",
      "trois"
    ],
    "answer": "trois",
    "points": 10
  },
  {
    "id": "L1-NU-04",
    "level": 1,
    "topic": "Numbers",
    "type": "multiple-choice",
    "question": "What is 'quatre' in English?",
    "options": [
      "3",
      "5",
      "4",
      "6"
    ],
    "answer": "4",
    "points": 10
  },
  {
    "id": "L1-NU-05",
    "level": 1,
    "topic": "Numbers",
    "type": "multiple-choice",
    "question": "How do you say '5' in French?",
    "options": [
      "six",
      "quatre",
      "cinq",
      "sept"
    ],
    "answer": "cinq",
    "points": 10
  },
  {
    "id": "L1-NU-06",
    "level": 1,
    "topic": "Numbers",
    "type": "multiple-choice",
    "question": "What is 'six' in English?",
    "options": [
      "7",
      "5",
      "6",
      "8"
    ],
    "answer": "6",
    "points": 10
  },
  {
    "id": "L1-NU-07",
    "level": 1,
    "topic": "Numbers",
    "type": "multiple-choice",
    "question": "How do you say '7' in French?",
    "options": [
      "huit",
      "six",
      "neuf",
      "sept"
    ],
    "answer": "sept",
    "points": 10
  },
  {
    "id": "L1-NU-08",
    "level": 1,
    "topic": "Numbers",
    "type": "multiple-choice",
    "question": "What is 'huit' in English?",
    "options": [
      "6",
      "9",
      "8",
      "7"
    ],
    "answer": "8",
    "points": 10
  },
  {
    "id": "L1-NU-09",
    "level": 1,
    "topic": "Numbers",
    "type": "multiple-choice",
    "question": "How do you say '9' in French?",
    "options": [
      "huit",
      "dix",
      "sept",
      "neuf"
    ],
    "answer": "neuf",
    "points": 10
  },
  {
    "id": "L1-NU-10",
    "level": 1,
    "topic": "Numbers",
    "type": "multiple-choice",
    "question": "What is 'dix' in English?",
    "options": [
      "8",
      "10",
      "11",
      "9"
    ],
    "answer": "10",
    "points": 10
  },
  {
    "id": "L1-FO-01",
    "level": 1,
    "topic": "Food",
    "type": "picture-match",
    "question": "Which word matches this picture?",
    "image": "🍎",
    "options": [
      "la banane",
      "la pomme",
      "l'orange",
      "le raisin"
    ],
    "answer": "la pomme",
    "points": 10,
    "hint": "A fruit that can be red or green"
  },
  {
    "id": "L1-FO-02",
    "level": 1,
    "topic": "Food",
    "type": "picture-match",
    "question": "Which word matches this picture?",
    "image": "🍌",
    "options": [
      "la pomme",
      "la banane",
      "la fraise",
      "la poire"
    ],
    "answer": "la banane",
    "points": 10
  },
  {
    "id": "L1-FO-03",
    "level": 1,
    "topic": "Food",
    "type": "multiple-choice",
    "question": "What is 'le pain' in English?",
    "options": [
      "milk",
      "bread",
      "cake",
      "egg"
    ],
    "answer": "bread",
    "points": 10
  },
  {
    "id": "L1-FO-04",
    "level": 1,
    "topic": "Food",
    "type": "multiple-choice",
    "question": "How do you say 'milk' in French?",
    "options": [
      "le jus",
      "l'eau",
      "le lait",
      "le thé"
    ],
    "answer": "le lait",
    "points": 10
  },
  {
    "id": "L1-FO-05",
    "level": 1,
    "topic": "Food",
    "type": "picture-match",
    "question": "Which word matches this picture?",
    "image": "🥚",
    "options": [
      "le fromage",
      "le beurre",
      "l'oeuf",
      "le lait"
    ],
    "answer": "l'oeuf",
    "points": 10
  },
  {
    "id": "L1-FO-06",
    "level": 1,
    "topic": "Food",
    "type": "multiple-choice",
    "question": "What is 'le fromage' in English?",
    "options": [
      "butter",
      "yogurt",
      "cheese",
      "cream"
    ],
    "answer": "cheese",
    "points": 10
  },
  {
    "id": "L1-FO-07",
    "level": 1,
    "topic": "Food",
    "type": "picture-match",
    "question": "Which word matches this picture?",
    "image": "🍓",
    "options": [
      "la poire",
      "la fraise",
      "la cerise",
      "la pomme"
    ],
    "answer": "la fraise",
    "points": 10
  },
  {
    "id": "L1-FO-08",
    "level": 1,
    "topic": "Food",
    "type": "multiple-choice",
    "question": "How do you say 'water' in French?",
    "options": [
      "le jus",
      "le lait",
      "le thé",
      "l'eau"
    ],
    "answer": "l'eau",
    "points": 10
  },
  {
    "id": "L1-FO-09",
    "level": 1,
    "topic": "Food",
    "type": "multiple-choice",
    "question": "What is 'le gâteau' in English?",
    "options": [
      "biscuit",
      "cake",
      "pie",
      "bread"
    ],
    "answer": "cake",
    "points": 10
  },
  {
    "id": "L1-FO-10",
    "level": 1,
    "topic": "Food",
    "type": "picture-match",
    "question": "Which word matches this picture?",
    "image": "🍊",
    "options": [
      "le citron",
      "la pomme",
      "l'orange",
      "la banane"
    ],
    "answer": "l'orange",
    "points": 10
  },
  {
    "id": "L1-FA-01",
    "level": 1,
    "topic": "Family",
    "type": "multiple-choice",
    "question": "What is 'la mère' in English?",
    "options": [
      "sister",
      "grandmother",
      "mother",
      "aunt"
    ],
    "answer": "mother",
    "points": 10
  },
  {
    "id": "L1-FA-02",
    "level": 1,
    "topic": "Family",
    "type": "multiple-choice",
    "question": "How do you say 'father' in French?",
    "options": [
      "le frère",
      "le père",
      "l'oncle",
      "le fils"
    ],
    "answer": "le père",
    "points": 10
  },
  {
    "id": "L1-FA-03",
    "level": 1,
    "topic": "Family",
    "type": "multiple-choice",
    "question": "What is 'le frère' in English?",
    "options": [
      "cousin",
      "uncle",
      "son",
      "brother"
    ],
    "answer": "brother",
    "points": 10
  },
  {
    "id": "L1-FA-04",
    "level": 1,
    "topic": "Family",
    "type": "multiple-choice",
    "question": "How do you say 'sister' in French?",
    "options": [
      "la cousine",
      "la tante",
      "la soeur",
      "la fille"
    ],
    "answer": "la soeur",
    "points": 10
  },
  {
    "id": "L1-FA-05",
    "level": 1,
    "topic": "Family",
    "type": "picture-match",
    "question": "Who is this?",
    "image": "👴",
    "options": [
      "le père",
      "l'oncle",
      "le grand-père",
      "le frère"
    ],
    "answer": "le grand-père",
    "points": 10
  },
  {
    "id": "L1-FA-06",
    "level": 1,
    "topic": "Family",
    "type": "picture-match",
    "question": "Who is this?",
    "image": "👵",
    "options": [
      "la mère",
      "la tante",
      "la soeur",
      "la grand-mère"
    ],
    "answer": "la grand-mère",
    "points": 10
  },
  {
    "id": "L1-FA-07",
    "level": 1,
    "topic": "Family",
    "type": "multiple-choice",
    "question": "What is 'le fils' in English?",
    "options": [
      "nephew",
      "brother",
      "son",
      "cousin"
    ],
    "answer": "son",
    "points": 10
  },
  {
    "id": "L1-FA-08",
    "level": 1,
    "topic": "Family",
    "type": "multiple-choice",
    "question": "How do you say 'aunt' in French?",
    "options": [
      "la cousine",
      "la niece",
      "la tante",
      "la soeur"
    ],
    "answer": "la tante",
    "points": 10
  },
  {
    "id": "L1-FA-09",
    "level": 1,
    "topic": "Family",
    "type": "multiple-choice",
    "question": "What is 'l'oncle' in English?",
    "options": [
      "cousin",
      "uncle",
      "nephew",
      "brother"
    ],
    "answer": "uncle",
    "points": 10
  },
  {
    "id": "L1-FA-10",
    "level": 1,
    "topic": "Family",
    "type": "multiple-choice",
    "question": "How do you say 'baby' in French?",
    "options": [
      "l'enfant",
      "le garçon",
      "le bébé",
      "le fils"
    ],
    "answer": "le bébé",
    "points": 10
  },
  {
    "id": "L1-BO-01",
    "level": 1,
    "topic": "Body parts",
    "type": "picture-match",
    "question": "What body part is highlighted?",
    "image": "👁️",
    "options": [
      "le nez",
      "l'oreille",
      "l'oeil",
      "la bouche"
    ],
    "answer": "l'oeil",
    "points": 10
  },
  {
    "id": "L1-BO-02",
    "level": 1,
    "topic": "Body parts",
    "type": "multiple-choice",
    "question": "What is 'le nez' in English?",
    "options": [
      "ear",
      "mouth",
      "nose",
      "eye"
    ],
    "answer": "nose",
    "points": 10
  },
  {
    "id": "L1-BO-03",
    "level": 1,
    "topic": "Body parts",
    "type": "picture-match",
    "question": "What body part is highlighted?",
    "image": "👂",
    "options": [
      "la tête",
      "le nez",
      "la bouche",
      "l'oreille"
    ],
    "answer": "l'oreille",
    "points": 10
  },
  {
    "id": "L1-BO-04",
    "level": 1,
    "topic": "Body parts",
    "type": "multiple-choice",
    "question": "How do you say 'mouth' in French?",
    "options": [
      "l'oeil",
      "le nez",
      "la bouche",
      "la dent"
    ],
    "answer": "la bouche",
    "points": 10
  },
  {
    "id": "L1-BO-05",
    "level": 1,
    "topic": "Body parts",
    "type": "picture-match",
    "question": "What body part is highlighted?",
    "image": "🦶",
    "options": [
      "la main",
      "le bras",
      "le pied",
      "la jambe"
    ],
    "answer": "le pied",
    "points": 10
  },
  {
    "id": "L1-BO-06",
    "level": 1,
    "topic": "Body parts",
    "type": "multiple-choice",
    "question": "What is 'la main' in English?",
    "options": [
      "arm",
      "finger",
      "hand",
      "leg"
    ],
    "answer": "hand",
    "points": 10
  },
  {
    "id": "L1-BO-07",
    "level": 1,
    "topic": "Body parts",
    "type": "multiple-choice",
    "question": "How do you say 'head' in French?",
    "options": [
      "le cou",
      "la tête",
      "le dos",
      "le ventre"
    ],
    "answer": "la tête",
    "points": 10
  },
  {
    "id": "L1-BO-08",
    "level": 1,
    "topic": "Body parts",
    "type": "multiple-choice",
    "question": "What is 'le bras' in English?",
    "options": [
      "leg",
      "shoulder",
      "arm",
      "elbow"
    ],
    "answer": "arm",
    "points": 10
  },
  {
    "id": "L1-BO-09",
    "level": 1,
    "topic": "Body parts",
    "type": "picture-match",
    "question": "What body part is highlighted?",
    "image": "🦵",
    "options": [
      "le pied",
      "le genou",
      "la jambe",
      "la cheville"
    ],
    "answer": "la jambe",
    "points": 10
  },
  {
    "id": "L1-BO-10",
    "level": 1,
    "topic": "Body parts",
    "type": "multiple-choice",
    "question": "How do you say 'back' in French?",
    "options": [
      "le ventre",
      "la poitrine",
      "l'épaule",
      "le dos"
    ],
    "answer": "le dos",
    "points": 10
  },
  {
    "id": "L2-GR-01",
    "level": 2,
    "topic": "Greetings",
    "type": "multiple-choice",
    "question": "How do you say 'Hello' formally in French?",
    "options": [
      "Salut",
      "Bonjour",
      "Bonsoir",
      "Ciao"
    ],
    "answer": "Bonjour",
    "points": 20
  },
  {
    "id": "L2-GR-02",
    "level": 2,
    "topic": "Greetings",
    "type": "multiple-choice",
    "question": "What does 'Au revoir' mean?",
    "options": [
      "Good morning",
      "See you later",
      "Goodbye",
      "Good evening"
    ],
    "answer": "Goodbye",
    "points": 20
  },
  {
    "id": "L2-GR-03",
    "level": 2,
    "topic": "Greetings",
    "type": "fill-in-blank",
    "question": "Complete: 'Comment ___ appelez-vous?' (What is your name?)",
    "options": [
      "vous",
      "tu",
      "je",
      "il"
    ],
    "answer": "vous",
    "points": 20
  },
  {
    "id": "L2-GR-04",
    "level": 2,
    "topic": "Greetings",
    "type": "multiple-choice",
    "question": "How do you say 'My name is' in French?",
    "options": [
      "Je suis",
      "J'ai",
      "Je m'appelle",
      "Je veux"
    ],
    "answer": "Je m'appelle",
    "points": 20
  },
  {
    "id": "L2-GR-05",
    "level": 2,
    "topic": "Greetings",
    "type": "fill-in-blank",
    "question": "Complete: 'Comment ___ vas?' (How are you — informal)",
    "options": [
      "tu",
      "vous",
      "il",
      "je"
    ],
    "answer": "tu",
    "points": 20
  },
  {
    "id": "L2-GR-06",
    "level": 2,
    "topic": "Greetings",
    "type": "multiple-choice",
    "question": "What does 'Enchanté(e)' mean?",
    "options": [
      "Goodbye",
      "Thank you",
      "Nice to meet you",
      "Good night"
    ],
    "answer": "Nice to meet you",
    "points": 20
  },
  {
    "id": "L2-GR-07",
    "level": 2,
    "topic": "Greetings",
    "type": "multiple-choice",
    "question": "How do you say 'Good night' in French?",
    "options": [
      "Bonsoir",
      "Bonne nuit",
      "Bonjour",
      "À bientôt"
    ],
    "answer": "Bonne nuit",
    "points": 20
  },
  {
    "id": "L2-GR-08",
    "level": 2,
    "topic": "Greetings",
    "type": "fill-in-blank",
    "question": "Complete: 'Merci ___!' (Thank you very much!)",
    "options": [
      "beaucoup",
      "bien",
      "bon",
      "beau"
    ],
    "answer": "beaucoup",
    "points": 20
  },
  {
    "id": "L2-GR-09",
    "level": 2,
    "topic": "Greetings",
    "type": "multiple-choice",
    "question": "What does 'S'il vous plaît' mean?",
    "options": [
      "Excuse me",
      "Sorry",
      "Please",
      "Thank you"
    ],
    "answer": "Please",
    "points": 20
  },
  {
    "id": "L2-GR-10",
    "level": 2,
    "topic": "Greetings",
    "type": "multiple-choice",
    "question": "How do you say 'See you soon' in French?",
    "options": [
      "Au revoir",
      "Bonne nuit",
      "À bientôt",
      "Salut"
    ],
    "answer": "À bientôt",
    "points": 20
  },
  {
    "id": "L2-NU-01",
    "level": 2,
    "topic": "Numbers",
    "type": "multiple-choice",
    "question": "What is 'onze' in English?",
    "options": [
      "10",
      "12",
      "11",
      "13"
    ],
    "answer": "11",
    "points": 20
  },
  {
    "id": "L2-NU-02",
    "level": 2,
    "topic": "Numbers",
    "type": "multiple-choice",
    "question": "How do you say '15' in French?",
    "options": [
      "quatorze",
      "seize",
      "quinze",
      "treize"
    ],
    "answer": "quinze",
    "points": 20
  },
  {
    "id": "L2-NU-03",
    "level": 2,
    "topic": "Numbers",
    "type": "fill-in-blank",
    "question": "Fill in: 'dix-___ ' = 17",
    "options": [
      "sept",
      "huit",
      "six",
      "neuf"
    ],
    "answer": "sept",
    "points": 20
  },
  {
    "id": "L2-NU-04",
    "level": 2,
    "topic": "Numbers",
    "type": "multiple-choice",
    "question": "What is 'vingt' in English?",
    "options": [
      "12",
      "20",
      "22",
      "30"
    ],
    "answer": "20",
    "points": 20
  },
  {
    "id": "L2-NU-05",
    "level": 2,
    "topic": "Numbers",
    "type": "multiple-choice",
    "question": "How do you say '30' in French?",
    "options": [
      "vingt",
      "quarante",
      "trente",
      "cinquante"
    ],
    "answer": "trente",
    "points": 20
  },
  {
    "id": "L2-NU-06",
    "level": 2,
    "topic": "Numbers",
    "type": "fill-in-blank",
    "question": "Fill in: 'quarante-___' = 45",
    "options": [
      "cinq",
      "six",
      "sept",
      "quatre"
    ],
    "answer": "cinq",
    "points": 20
  },
  {
    "id": "L2-NU-07",
    "level": 2,
    "topic": "Numbers",
    "type": "multiple-choice",
    "question": "What is 'soixante' in English?",
    "options": [
      "50",
      "70",
      "60",
      "80"
    ],
    "answer": "60",
    "points": 20
  },
  {
    "id": "L2-NU-08",
    "level": 2,
    "topic": "Numbers",
    "type": "multiple-choice",
    "question": "How do you say '80' in French?",
    "options": [
      "quatre-vingts",
      "soixante-dix",
      "soixante",
      "quatre-vingt-dix"
    ],
    "answer": "quatre-vingts",
    "points": 20
  },
  {
    "id": "L2-NU-09",
    "level": 2,
    "topic": "Numbers",
    "type": "fill-in-blank",
    "question": "Fill in: 'quatre-vingt-___' = 90",
    "options": [
      "dix",
      "onze",
      "douze",
      "neuf"
    ],
    "answer": "dix",
    "points": 20
  },
  {
    "id": "L2-NU-10",
    "level": 2,
    "topic": "Numbers",
    "type": "multiple-choice",
    "question": "What is 'cent' in English?",
    "options": [
      "10",
      "50",
      "100",
      "1000"
    ],
    "answer": "100",
    "points": 20
  },
  {
    "id": "L2-CL-01",
    "level": 2,
    "topic": "Clothes",
    "type": "picture-match",
    "question": "Which word matches this item?",
    "image": "👕",
    "options": [
      "le pantalon",
      "le pull",
      "le t-shirt",
      "la veste"
    ],
    "answer": "le t-shirt",
    "points": 20
  },
  {
    "id": "L2-CL-02",
    "level": 2,
    "topic": "Clothes",
    "type": "multiple-choice",
    "question": "What is 'le pantalon' in English?",
    "options": [
      "skirt",
      "shorts",
      "trousers",
      "jeans"
    ],
    "answer": "trousers",
    "points": 20
  },
  {
    "id": "L2-CL-03",
    "level": 2,
    "topic": "Clothes",
    "type": "picture-match",
    "question": "Which word matches this item?",
    "image": "👗",
    "options": [
      "la jupe",
      "la robe",
      "le manteau",
      "le pull"
    ],
    "answer": "la robe",
    "points": 20
  },
  {
    "id": "L2-CL-04",
    "level": 2,
    "topic": "Clothes",
    "type": "fill-in-blank",
    "question": "Complete: 'Je porte un ___.' (I am wearing a coat.)",
    "options": [
      "manteau",
      "chapeau",
      "pull",
      "short"
    ],
    "answer": "manteau",
    "points": 20
  },
  {
    "id": "L2-CL-05",
    "level": 2,
    "topic": "Clothes",
    "type": "multiple-choice",
    "question": "How do you say 'shoes' in French?",
    "options": [
      "les chaussettes",
      "les chaussures",
      "les bottes",
      "les sandales"
    ],
    "answer": "les chaussures",
    "points": 20
  },
  {
    "id": "L2-CL-06",
    "level": 2,
    "topic": "Clothes",
    "type": "picture-match",
    "question": "Which word matches this item?",
    "image": "🧢",
    "options": [
      "le chapeau",
      "le bonnet",
      "la casquette",
      "l'écharpe"
    ],
    "answer": "la casquette",
    "points": 20
  },
  {
    "id": "L2-CL-07",
    "level": 2,
    "topic": "Clothes",
    "type": "multiple-choice",
    "question": "What is 'les chaussettes' in English?",
    "options": [
      "shoes",
      "boots",
      "socks",
      "sandals"
    ],
    "answer": "socks",
    "points": 20
  },
  {
    "id": "L2-CL-08",
    "level": 2,
    "topic": "Clothes",
    "type": "fill-in-blank",
    "question": "Complete: 'Il fait froid, mets ton ___!' (It's cold, put on your scarf!)",
    "options": [
      "écharpe",
      "short",
      "t-shirt",
      "chapeau"
    ],
    "answer": "écharpe",
    "points": 20
  },
  {
    "id": "L2-CL-09",
    "level": 2,
    "topic": "Clothes",
    "type": "multiple-choice",
    "question": "How do you say 'jacket' in French?",
    "options": [
      "le pull",
      "la chemise",
      "la veste",
      "le manteau"
    ],
    "answer": "la veste",
    "points": 20
  },
  {
    "id": "L2-CL-10",
    "level": 2,
    "topic": "Clothes",
    "type": "multiple-choice",
    "question": "What is 'le pull' in English?",
    "options": [
      "shirt",
      "jumper",
      "jacket",
      "coat"
    ],
    "answer": "jumper",
    "points": 20
  },
  {
    "id": "L2-SC-01",
    "level": 2,
    "topic": "School",
    "type": "picture-match",
    "question": "Which word matches this item?",
    "image": "📚",
    "options": [
      "le stylo",
      "le cahier",
      "les livres",
      "la règle"
    ],
    "answer": "les livres",
    "points": 20
  },
  {
    "id": "L2-SC-02",
    "level": 2,
    "topic": "School",
    "type": "multiple-choice",
    "question": "What is 'le stylo' in English?",
    "options": [
      "pencil",
      "pen",
      "ruler",
      "eraser"
    ],
    "answer": "pen",
    "points": 20
  },
  {
    "id": "L2-SC-03",
    "level": 2,
    "topic": "School",
    "type": "fill-in-blank",
    "question": "Complete: 'J'aime les ___.' (I like maths.)",
    "options": [
      "mathématiques",
      "sciences",
      "arts",
      "langues"
    ],
    "answer": "mathématiques",
    "points": 20
  },
  {
    "id": "L2-SC-04",
    "level": 2,
    "topic": "School",
    "type": "multiple-choice",
    "question": "How do you say 'classroom' in French?",
    "options": [
      "la cour",
      "la salle de classe",
      "la bibliothèque",
      "le gymnase"
    ],
    "answer": "la salle de classe",
    "points": 20
  },
  {
    "id": "L2-SC-05",
    "level": 2,
    "topic": "School",
    "type": "multiple-choice",
    "question": "What is 'le professeur' in English?",
    "options": [
      "student",
      "principal",
      "teacher",
      "parent"
    ],
    "answer": "teacher",
    "points": 20
  },
  {
    "id": "L2-SC-06",
    "level": 2,
    "topic": "School",
    "type": "picture-match",
    "question": "Which word matches this item?",
    "image": "📐",
    "options": [
      "la gomme",
      "le crayon",
      "la règle",
      "le taille-crayon"
    ],
    "answer": "la règle",
    "points": 20
  },
  {
    "id": "L2-SC-07",
    "level": 2,
    "topic": "School",
    "type": "fill-in-blank",
    "question": "Complete: 'Ouvre ton ___.' (Open your notebook.)",
    "options": [
      "cahier",
      "livre",
      "stylo",
      "sac"
    ],
    "answer": "cahier",
    "points": 20
  },
  {
    "id": "L2-SC-08",
    "level": 2,
    "topic": "School",
    "type": "multiple-choice",
    "question": "What is 'la récréation' in English?",
    "options": [
      "lunch",
      "break time",
      "homework",
      "lesson"
    ],
    "answer": "break time",
    "points": 20
  },
  {
    "id": "L2-SC-09",
    "level": 2,
    "topic": "School",
    "type": "multiple-choice",
    "question": "How do you say 'library' in French?",
    "options": [
      "le gymnase",
      "la salle de classe",
      "la bibliothèque",
      "la cantine"
    ],
    "answer": "la bibliothèque",
    "points": 20
  },
  {
    "id": "L2-SC-10",
    "level": 2,
    "topic": "School",
    "type": "fill-in-blank",
    "question": "Complete: 'Mon ___ préféré est l'histoire.' (My favourite subject is history.)",
    "options": [
      "matière",
      "livre",
      "professeur",
      "jour"
    ],
    "answer": "matière",
    "points": 20
  },
  {
    "id": "L2-WE-01",
    "level": 2,
    "topic": "Weather",
    "type": "picture-match",
    "question": "What is the weather?",
    "image": "☀️",
    "options": [
      "Il pleut",
      "Il neige",
      "Il fait soleil",
      "Il fait froid"
    ],
    "answer": "Il fait soleil",
    "points": 20
  },
  {
    "id": "L2-WE-02",
    "level": 2,
    "topic": "Weather",
    "type": "picture-match",
    "question": "What is the weather?",
    "image": "🌧️",
    "options": [
      "Il fait chaud",
      "Il pleut",
      "Il neige",
      "Il fait du vent"
    ],
    "answer": "Il pleut",
    "points": 20
  },
  {
    "id": "L2-WE-03",
    "level": 2,
    "topic": "Weather",
    "type": "multiple-choice",
    "question": "What does 'Il neige' mean?",
    "options": [
      "It is windy",
      "It is raining",
      "It is snowing",
      "It is cloudy"
    ],
    "answer": "It is snowing",
    "points": 20
  },
  {
    "id": "L2-WE-04",
    "level": 2,
    "topic": "Weather",
    "type": "fill-in-blank",
    "question": "Complete: 'Il fait ___ aujourd'hui, mets un manteau!' (It is cold today, put on a coat!)",
    "options": [
      "froid",
      "chaud",
      "beau",
      "mauvais"
    ],
    "answer": "froid",
    "points": 20
  },
  {
    "id": "L2-WE-05",
    "level": 2,
    "topic": "Weather",
    "type": "multiple-choice",
    "question": "How do you say 'It is windy' in French?",
    "options": [
      "Il fait du brouillard",
      "Il fait du vent",
      "Il fait de l'orage",
      "Il grêle"
    ],
    "answer": "Il fait du vent",
    "points": 20
  },
  {
    "id": "L2-WE-06",
    "level": 2,
    "topic": "Weather",
    "type": "multiple-choice",
    "question": "What is 'le nuage' in English?",
    "options": [
      "rain",
      "sun",
      "snow",
      "cloud"
    ],
    "answer": "cloud",
    "points": 20
  },
  {
    "id": "L2-WE-07",
    "level": 2,
    "topic": "Weather",
    "type": "fill-in-blank",
    "question": "Complete: 'Quel ___ fait-il?' (What is the weather like?)",
    "options": [
      "temps",
      "jour",
      "saison",
      "mois"
    ],
    "answer": "temps",
    "points": 20
  },
  {
    "id": "L2-WE-08",
    "level": 2,
    "topic": "Weather",
    "type": "multiple-choice",
    "question": "What does 'Il fait chaud' mean?",
    "options": [
      "It is cold",
      "It is warm",
      "It is cloudy",
      "It is foggy"
    ],
    "answer": "It is warm",
    "points": 20
  },
  {
    "id": "L2-WE-09",
    "level": 2,
    "topic": "Weather",
    "type": "multiple-choice",
    "question": "How do you say 'thunder' in French?",
    "options": [
      "l'éclair",
      "la pluie",
      "la grêle",
      "le tonnerre"
    ],
    "answer": "le tonnerre",
    "points": 20
  },
  {
    "id": "L2-WE-10",
    "level": 2,
    "topic": "Weather",
    "type": "picture-match",
    "question": "What is the weather?",
    "image": "⛅",
    "options": [
      "Il fait soleil",
      "Il neige",
      "Il fait nuageux",
      "Il pleut"
    ],
    "answer": "Il fait nuageux",
    "points": 20
  },
  {
    "id": "L2-TR-01",
    "level": 2,
    "topic": "Transport",
    "type": "picture-match",
    "question": "Which word matches this picture?",
    "image": "🚗",
    "options": [
      "le bus",
      "le train",
      "la voiture",
      "le vélo"
    ],
    "answer": "la voiture",
    "points": 20
  },
  {
    "id": "L2-TR-02",
    "level": 2,
    "topic": "Transport",
    "type": "multiple-choice",
    "question": "What is 'le train' in English?",
    "options": [
      "bus",
      "tram",
      "train",
      "metro"
    ],
    "answer": "train",
    "points": 20
  },
  {
    "id": "L2-TR-03",
    "level": 2,
    "topic": "Transport",
    "type": "fill-in-blank",
    "question": "Complete: 'Je vais à l'école en ___.' (I go to school by bus.)",
    "options": [
      "bus",
      "train",
      "voiture",
      "vélo"
    ],
    "answer": "bus",
    "points": 20
  },
  {
    "id": "L2-TR-04",
    "level": 2,
    "topic": "Transport",
    "type": "picture-match",
    "question": "Which word matches this picture?",
    "image": "✈️",
    "options": [
      "le bateau",
      "le bus",
      "l'avion",
      "la moto"
    ],
    "answer": "l'avion",
    "points": 20
  },
  {
    "id": "L2-TR-05",
    "level": 2,
    "topic": "Transport",
    "type": "multiple-choice",
    "question": "How do you say 'bicycle' in French?",
    "options": [
      "la moto",
      "le scooter",
      "le vélo",
      "le skateboard"
    ],
    "answer": "le vélo",
    "points": 20
  },
  {
    "id": "L2-TR-06",
    "level": 2,
    "topic": "Transport",
    "type": "multiple-choice",
    "question": "What is 'le bateau' in English?",
    "options": [
      "plane",
      "boat",
      "train",
      "car"
    ],
    "answer": "boat",
    "points": 20
  },
  {
    "id": "L2-TR-07",
    "level": 2,
    "topic": "Transport",
    "type": "fill-in-blank",
    "question": "Complete: 'Le ___ arrive à la gare.' (The train arrives at the station.)",
    "options": [
      "train",
      "bus",
      "vélo",
      "avion"
    ],
    "answer": "train",
    "points": 20
  },
  {
    "id": "L2-TR-08",
    "level": 2,
    "topic": "Transport",
    "type": "multiple-choice",
    "question": "How do you say 'underground/metro' in French?",
    "options": [
      "le tramway",
      "le bus",
      "la voiture",
      "le métro"
    ],
    "answer": "le métro",
    "points": 20
  },
  {
    "id": "L2-TR-09",
    "level": 2,
    "topic": "Transport",
    "type": "picture-match",
    "question": "Which word matches this picture?",
    "image": "🚢",
    "options": [
      "le bateau",
      "le ferry",
      "le sous-marin",
      "le yacht"
    ],
    "answer": "le bateau",
    "points": 20
  },
  {
    "id": "L2-TR-10",
    "level": 2,
    "topic": "Transport",
    "type": "multiple-choice",
    "question": "What is 'à pied' in English?",
    "options": [
      "by car",
      "by bike",
      "by bus",
      "on foot"
    ],
    "answer": "on foot",
    "points": 20
  },
  {
    "id": "L3-EM-01",
    "level": 3,
    "topic": "Emotions",
    "type": "multiple-choice",
    "question": "What does 'Je suis content(e)' mean?",
    "options": [
      "I am sad",
      "I am angry",
      "I am happy",
      "I am tired"
    ],
    "answer": "I am happy",
    "points": 30
  },
  {
    "id": "L3-EM-02",
    "level": 3,
    "topic": "Emotions",
    "type": "sentence-build",
    "question": "Build the sentence: 'I am very tired today'",
    "words": [
      "très",
      "suis",
      "aujourd'hui",
      "fatigué(e)",
      "Je"
    ],
    "answer": [
      "Je",
      "suis",
      "très",
      "fatigué(e)",
      "aujourd'hui"
    ],
    "points": 30
  },
  {
    "id": "L3-EM-03",
    "level": 3,
    "topic": "Emotions",
    "type": "fill-in-blank",
    "question": "Complete: 'Il est ___ parce qu'il a perdu.' (He is sad because he lost.)",
    "options": [
      "triste",
      "content",
      "énervé",
      "surpris"
    ],
    "answer": "triste",
    "points": 30
  },
  {
    "id": "L3-EM-04",
    "level": 3,
    "topic": "Emotions",
    "type": "multiple-choice",
    "question": "How do you say 'I am scared' in French?",
    "options": [
      "Je suis surpris",
      "J'ai peur",
      "Je suis jaloux",
      "Je suis honteux"
    ],
    "answer": "J'ai peur",
    "points": 30
  },
  {
    "id": "L3-EM-05",
    "level": 3,
    "topic": "Emotions",
    "type": "sentence-build",
    "question": "Build: 'She is angry because of the noise'",
    "words": [
      "est",
      "Elle",
      "à cause du",
      "bruit",
      "énervée"
    ],
    "answer": [
      "Elle",
      "est",
      "énervée",
      "à cause du",
      "bruit"
    ],
    "points": 30
  },
  {
    "id": "L3-EM-06",
    "level": 3,
    "topic": "Emotions",
    "type": "multiple-choice",
    "question": "What does 'Je me sens bien' mean?",
    "options": [
      "I feel sick",
      "I feel well",
      "I feel nervous",
      "I feel bored"
    ],
    "answer": "I feel well",
    "points": 30
  },
  {
    "id": "L3-EM-07",
    "level": 3,
    "topic": "Emotions",
    "type": "fill-in-blank",
    "question": "Complete: 'Nous sommes ___ de te voir!' (We are delighted to see you!)",
    "options": [
      "ravis",
      "tristes",
      "inquiets",
      "déçus"
    ],
    "answer": "ravis",
    "points": 30
  },
  {
    "id": "L3-EM-08",
    "level": 3,
    "topic": "Emotions",
    "type": "multiple-choice",
    "question": "What is 'la jalousie' in English?",
    "options": [
      "sadness",
      "anger",
      "jealousy",
      "fear"
    ],
    "answer": "jealousy",
    "points": 30
  },
  {
    "id": "L3-EM-09",
    "level": 3,
    "topic": "Emotions",
    "type": "sentence-build",
    "question": "Build: 'I am proud of my work'",
    "words": [
      "mon",
      "suis",
      "de",
      "travail",
      "fier/fière",
      "Je"
    ],
    "answer": [
      "Je",
      "suis",
      "fier/fière",
      "de",
      "mon",
      "travail"
    ],
    "points": 30
  },
  {
    "id": "L3-EM-10",
    "level": 3,
    "topic": "Emotions",
    "type": "multiple-choice",
    "question": "How do you say 'I am bored' in French?",
    "options": [
      "Je suis triste",
      "Je m'ennuie",
      "Je suis fatigué",
      "Je suis déçu"
    ],
    "answer": "Je m'ennuie",
    "points": 30
  },
  {
    "id": "L3-NA-01",
    "level": 3,
    "topic": "Nature",
    "type": "multiple-choice",
    "question": "What is 'la forêt' in English?",
    "options": [
      "mountain",
      "forest",
      "river",
      "beach"
    ],
    "answer": "forest",
    "points": 30
  },
  {
    "id": "L3-NA-02",
    "level": 3,
    "topic": "Nature",
    "type": "fill-in-blank",
    "question": "Complete: 'La ___ coule vers la mer.' (The river flows to the sea.)",
    "options": [
      "rivière",
      "montagne",
      "forêt",
      "vallée"
    ],
    "answer": "rivière",
    "points": 30
  },
  {
    "id": "L3-NA-03",
    "level": 3,
    "topic": "Nature",
    "type": "sentence-build",
    "question": "Build: 'The mountains are covered in snow'",
    "words": [
      "sont",
      "de",
      "Les",
      "couvertes",
      "montagnes",
      "neige"
    ],
    "answer": [
      "Les",
      "montagnes",
      "sont",
      "couvertes",
      "de",
      "neige"
    ],
    "points": 30
  },
  {
    "id": "L3-NA-04",
    "level": 3,
    "topic": "Nature",
    "type": "multiple-choice",
    "question": "How do you say 'ocean' in French?",
    "options": [
      "la mer",
      "le lac",
      "l'océan",
      "la rivière"
    ],
    "answer": "l'océan",
    "points": 30
  },
  {
    "id": "L3-NA-05",
    "level": 3,
    "topic": "Nature",
    "type": "fill-in-blank",
    "question": "Complete: 'Les ___ fleurissent au printemps.' (The flowers bloom in spring.)",
    "options": [
      "fleurs",
      "arbres",
      "feuilles",
      "herbes"
    ],
    "answer": "fleurs",
    "points": 30
  },
  {
    "id": "L3-NA-06",
    "level": 3,
    "topic": "Nature",
    "type": "multiple-choice",
    "question": "What is 'le volcan' in English?",
    "options": [
      "earthquake",
      "tornado",
      "volcano",
      "tsunami"
    ],
    "answer": "volcano",
    "points": 30
  },
  {
    "id": "L3-NA-07",
    "level": 3,
    "topic": "Nature",
    "type": "sentence-build",
    "question": "Build: 'We must protect the environment'",
    "words": [
      "protéger",
      "l'environnement",
      "devons",
      "Nous"
    ],
    "answer": [
      "Nous",
      "devons",
      "protéger",
      "l'environnement"
    ],
    "points": 30
  },
  {
    "id": "L3-NA-08",
    "level": 3,
    "topic": "Nature",
    "type": "multiple-choice",
    "question": "What is 'la désertification' in English?",
    "options": [
      "flooding",
      "erosion",
      "desertification",
      "deforestation"
    ],
    "answer": "desertification",
    "points": 30
  },
  {
    "id": "L3-NA-09",
    "level": 3,
    "topic": "Nature",
    "type": "fill-in-blank",
    "question": "Complete: 'Le ___ est indispensable à la vie.' (Water is essential to life.)",
    "options": [
      "eau",
      "feu",
      "vent",
      "sol"
    ],
    "answer": "eau",
    "points": 30
  },
  {
    "id": "L3-NA-10",
    "level": 3,
    "topic": "Nature",
    "type": "multiple-choice",
    "question": "How do you say 'endangered species' in French?",
    "options": [
      "espèce commune",
      "espèce en voie de disparition",
      "espèce protégée",
      "espèce invasive"
    ],
    "answer": "espèce en voie de disparition",
    "points": 30
  },
  {
    "id": "L3-DI-01",
    "level": 3,
    "topic": "Directions",
    "type": "multiple-choice",
    "question": "What does 'Tournez à gauche' mean?",
    "options": [
      "Go straight",
      "Turn right",
      "Turn left",
      "Go back"
    ],
    "answer": "Turn left",
    "points": 30
  },
  {
    "id": "L3-DI-02",
    "level": 3,
    "topic": "Directions",
    "type": "fill-in-blank",
    "question": "Complete: 'Continuez ___.' (Go straight ahead.)",
    "options": [
      "tout droit",
      "à gauche",
      "à droite",
      "en arrière"
    ],
    "answer": "tout droit",
    "points": 30
  },
  {
    "id": "L3-DI-03",
    "level": 3,
    "topic": "Directions",
    "type": "sentence-build",
    "question": "Build: 'The bakery is next to the post office'",
    "words": [
      "La",
      "boulangerie",
      "est",
      "à côté de",
      "la poste"
    ],
    "answer": [
      "La",
      "boulangerie",
      "est",
      "à côté de",
      "la poste"
    ],
    "points": 30
  },
  {
    "id": "L3-DI-04",
    "level": 3,
    "topic": "Directions",
    "type": "multiple-choice",
    "question": "How do you say 'Take the second street on the right' in French?",
    "options": [
      "Prenez la première rue à gauche",
      "Prenez la deuxième rue à droite",
      "Prenez la troisième rue tout droit",
      "Tournez à gauche"
    ],
    "answer": "Prenez la deuxième rue à droite",
    "points": 30
  },
  {
    "id": "L3-DI-05",
    "level": 3,
    "topic": "Directions",
    "type": "fill-in-blank",
    "question": "Complete: 'La gare est ___ le pont.' (The station is in front of the bridge.)",
    "options": [
      "devant",
      "derrière",
      "sous",
      "sur"
    ],
    "answer": "devant",
    "points": 30
  },
  {
    "id": "L3-DI-06",
    "level": 3,
    "topic": "Directions",
    "type": "multiple-choice",
    "question": "What is 'le carrefour' in English?",
    "options": [
      "bridge",
      "crossroads",
      "roundabout",
      "traffic light"
    ],
    "answer": "crossroads",
    "points": 30
  },
  {
    "id": "L3-DI-07",
    "level": 3,
    "topic": "Directions",
    "type": "sentence-build",
    "question": "Build: 'Excuse me, where is the museum?'",
    "words": [
      "Excusez-moi,",
      "où",
      "est",
      "le",
      "musée?"
    ],
    "answer": [
      "Excusez-moi,",
      "où",
      "est",
      "le",
      "musée?"
    ],
    "points": 30
  },
  {
    "id": "L3-DI-08",
    "level": 3,
    "topic": "Directions",
    "type": "multiple-choice",
    "question": "What does 'C'est loin d'ici' mean?",
    "options": [
      "It is near here",
      "It is far from here",
      "It is behind here",
      "It is next to here"
    ],
    "answer": "It is far from here",
    "points": 30
  },
  {
    "id": "L3-DI-09",
    "level": 3,
    "topic": "Directions",
    "type": "fill-in-blank",
    "question": "Complete: 'Traversez le ___.' (Cross the bridge.)",
    "options": [
      "pont",
      "carrefour",
      "trottoir",
      "rond-point"
    ],
    "answer": "pont",
    "points": 30
  },
  {
    "id": "L3-DI-10",
    "level": 3,
    "topic": "Directions",
    "type": "multiple-choice",
    "question": "How do you say 'opposite' in French?",
    "options": [
      "à côté de",
      "derrière",
      "en face de",
      "devant"
    ],
    "answer": "en face de",
    "points": 30
  },
  {
    "id": "L3-DR-01",
    "level": 3,
    "topic": "Daily routines",
    "type": "multiple-choice",
    "question": "What does 'Je me réveille' mean?",
    "options": [
      "I go to bed",
      "I wake up",
      "I get dressed",
      "I brush my teeth"
    ],
    "answer": "I wake up",
    "points": 30
  },
  {
    "id": "L3-DR-02",
    "level": 3,
    "topic": "Daily routines",
    "type": "sentence-build",
    "question": "Build: 'I brush my teeth every morning'",
    "words": [
      "Je",
      "me",
      "brosse",
      "les dents",
      "chaque matin"
    ],
    "answer": [
      "Je",
      "me",
      "brosse",
      "les dents",
      "chaque matin"
    ],
    "points": 30
  },
  {
    "id": "L3-DR-03",
    "level": 3,
    "topic": "Daily routines",
    "type": "fill-in-blank",
    "question": "Complete: 'Je ___ à sept heures.' (I have breakfast at seven o'clock.)",
    "options": [
      "prends le petit-déjeuner",
      "dîne",
      "déjeune",
      "goûte"
    ],
    "answer": "prends le petit-déjeuner",
    "points": 30
  },
  {
    "id": "L3-DR-04",
    "level": 3,
    "topic": "Daily routines",
    "type": "multiple-choice",
    "question": "How do you say 'I go to bed' in French?",
    "options": [
      "Je me lève",
      "Je me couche",
      "Je m'endors",
      "Je me repose"
    ],
    "answer": "Je me couche",
    "points": 30
  },
  {
    "id": "L3-DR-05",
    "level": 3,
    "topic": "Daily routines",
    "type": "sentence-build",
    "question": "Build: 'She gets dressed before breakfast'",
    "words": [
      "s'habille",
      "Elle",
      "avant",
      "le petit-déjeuner"
    ],
    "answer": [
      "Elle",
      "s'habille",
      "avant",
      "le petit-déjeuner"
    ],
    "points": 30
  },
  {
    "id": "L3-DR-06",
    "level": 3,
    "topic": "Daily routines",
    "type": "multiple-choice",
    "question": "What is 'faire la vaisselle' in English?",
    "options": [
      "do the laundry",
      "do the washing up",
      "make the bed",
      "vacuum"
    ],
    "answer": "do the washing up",
    "points": 30
  },
  {
    "id": "L3-DR-07",
    "level": 3,
    "topic": "Daily routines",
    "type": "fill-in-blank",
    "question": "Complete: 'Après le dîner, je ___ mes devoirs.' (After dinner, I do my homework.)",
    "options": [
      "fais",
      "lis",
      "joue",
      "regarde"
    ],
    "answer": "fais",
    "points": 30
  },
  {
    "id": "L3-DR-08",
    "level": 3,
    "topic": "Daily routines",
    "type": "multiple-choice",
    "question": "What does 'Je me douche' mean?",
    "options": [
      "I have a bath",
      "I wash my hands",
      "I shower",
      "I get dressed"
    ],
    "answer": "I shower",
    "points": 30
  },
  {
    "id": "L3-DR-09",
    "level": 3,
    "topic": "Daily routines",
    "type": "sentence-build",
    "question": "Build: 'We eat dinner at seven thirty'",
    "words": [
      "Nous",
      "dînons",
      "à",
      "sept heures et demie"
    ],
    "answer": [
      "Nous",
      "dînons",
      "à",
      "sept heures et demie"
    ],
    "points": 30
  },
  {
    "id": "L3-DR-10",
    "level": 3,
    "topic": "Daily routines",
    "type": "multiple-choice",
    "question": "How do you say 'to commute to work' in French?",
    "options": [
      "aller au lit",
      "faire les courses",
      "aller au travail",
      "rester à la maison"
    ],
    "answer": "aller au travail",
    "points": 30
  },
  {
    "id": "L3-VE-01",
    "level": 3,
    "topic": "Present tense verbs",
    "type": "fill-in-blank",
    "question": "Complete: 'Nous ___ au football.' (We play football.)",
    "options": [
      "jouons",
      "joue",
      "jouez",
      "jouent"
    ],
    "answer": "jouons",
    "points": 30
  },
  {
    "id": "L3-VE-02",
    "level": 3,
    "topic": "Present tense verbs",
    "type": "multiple-choice",
    "question": "Which is correct: 'They eat' in French?",
    "options": [
      "Ils mange",
      "Ils mangent",
      "Ils mangeons",
      "Ils mangez"
    ],
    "answer": "Ils mangent",
    "points": 30
  },
  {
    "id": "L3-VE-03",
    "level": 3,
    "topic": "Present tense verbs",
    "type": "sentence-build",
    "question": "Build: 'She reads a book every day'",
    "words": [
      "Elle",
      "lit",
      "un livre",
      "tous les jours"
    ],
    "answer": [
      "Elle",
      "lit",
      "un livre",
      "tous les jours"
    ],
    "points": 30
  },
  {
    "id": "L3-VE-04",
    "level": 3,
    "topic": "Present tense verbs",
    "type": "fill-in-blank",
    "question": "Complete: 'Tu ___ bien le français.' (You speak French well.)",
    "options": [
      "parles",
      "parle",
      "parlez",
      "parlons"
    ],
    "answer": "parles",
    "points": 30
  },
  {
    "id": "L3-VE-05",
    "level": 3,
    "topic": "Present tense verbs",
    "type": "multiple-choice",
    "question": "Which is the correct conjugation of 'avoir' for 'nous'?",
    "options": [
      "nous a",
      "nous as",
      "nous avez",
      "nous avons"
    ],
    "answer": "nous avons",
    "points": 30
  },
  {
    "id": "L3-VE-06",
    "level": 3,
    "topic": "Present tense verbs",
    "type": "sentence-build",
    "question": "Build: 'I write letters to my grandmother'",
    "words": [
      "J'écris",
      "des lettres",
      "à",
      "ma grand-mère"
    ],
    "answer": [
      "J'écris",
      "des lettres",
      "à",
      "ma grand-mère"
    ],
    "points": 30
  },
  {
    "id": "L3-VE-07",
    "level": 3,
    "topic": "Present tense verbs",
    "type": "fill-in-blank",
    "question": "Complete: 'Il ___ de la guitare.' (He plays guitar.)",
    "options": [
      "joue",
      "jouons",
      "jouez",
      "jouent"
    ],
    "answer": "joue",
    "points": 30
  },
  {
    "id": "L3-VE-08",
    "level": 3,
    "topic": "Present tense verbs",
    "type": "multiple-choice",
    "question": "Which is correct: 'You (formal) know' in French?",
    "options": [
      "tu sais",
      "vous savez",
      "il sait",
      "nous savons"
    ],
    "answer": "vous savez",
    "points": 30
  },
  {
    "id": "L3-VE-09",
    "level": 3,
    "topic": "Present tense verbs",
    "type": "fill-in-blank",
    "question": "Complete: 'Elles ___ à Paris.' (They live in Paris.)",
    "options": [
      "habitent",
      "habite",
      "habitons",
      "habitez"
    ],
    "answer": "habitent",
    "points": 30
  },
  {
    "id": "L3-VE-10",
    "level": 3,
    "topic": "Present tense verbs",
    "type": "sentence-build",
    "question": "Build: 'We are learning French at school'",
    "words": [
      "Nous",
      "apprenons",
      "le français",
      "à l'école"
    ],
    "answer": [
      "Nous",
      "apprenons",
      "le français",
      "à l'école"
    ],
    "points": 30
  },
  {
    "id": "L3-AD-01",
    "level": 3,
    "topic": "Adjectives",
    "type": "multiple-choice",
    "question": "What is the feminine form of 'grand'?",
    "options": [
      "grande",
      "grands",
      "grander",
      "grandes"
    ],
    "answer": "grande",
    "points": 30
  },
  {
    "id": "L3-AD-02",
    "level": 3,
    "topic": "Adjectives",
    "type": "fill-in-blank",
    "question": "Complete: 'C'est une ___ femme.' (She is a beautiful woman.)",
    "options": [
      "belle",
      "beau",
      "bel",
      "beaux"
    ],
    "answer": "belle",
    "points": 30
  },
  {
    "id": "L3-AD-03",
    "level": 3,
    "topic": "Adjectives",
    "type": "sentence-build",
    "question": "Build: 'The old house is very beautiful'",
    "words": [
      "La",
      "vieille",
      "maison",
      "est",
      "très",
      "belle"
    ],
    "answer": [
      "La",
      "vieille",
      "maison",
      "est",
      "très",
      "belle"
    ],
    "points": 30
  },
  {
    "id": "L3-AD-04",
    "level": 3,
    "topic": "Adjectives",
    "type": "multiple-choice",
    "question": "Where do most French adjectives go?",
    "options": [
      "Before the noun",
      "After the noun",
      "At the end of the sentence",
      "Before the verb"
    ],
    "answer": "After the noun",
    "points": 30
  },
  {
    "id": "L3-AD-05",
    "level": 3,
    "topic": "Adjectives",
    "type": "fill-in-blank",
    "question": "Complete: 'Il a les cheveux ___.' (He has long hair.)",
    "options": [
      "longs",
      "long",
      "longue",
      "longues"
    ],
    "answer": "longs",
    "points": 30
  },
  {
    "id": "L3-AD-06",
    "level": 3,
    "topic": "Adjectives",
    "type": "multiple-choice",
    "question": "What is the opposite of 'rapide' (fast)?",
    "options": [
      "fort",
      "lent",
      "petit",
      "lourd"
    ],
    "answer": "lent",
    "points": 30
  },
  {
    "id": "L3-AD-07",
    "level": 3,
    "topic": "Adjectives",
    "type": "sentence-build",
    "question": "Build: 'My new blue car is very fast'",
    "words": [
      "Ma",
      "nouvelle",
      "voiture",
      "bleue",
      "est",
      "très rapide"
    ],
    "answer": [
      "Ma",
      "nouvelle",
      "voiture",
      "bleue",
      "est",
      "très rapide"
    ],
    "points": 30
  },
  {
    "id": "L3-AD-08",
    "level": 3,
    "topic": "Adjectives",
    "type": "fill-in-blank",
    "question": "Complete: 'Cette fleur sent ___.' (This flower smells delicious.)",
    "options": [
      "délicieux",
      "délicieuse",
      "délicieuses",
      "délicieux"
    ],
    "answer": "délicieux",
    "points": 30
  },
  {
    "id": "L3-AD-09",
    "level": 3,
    "topic": "Adjectives",
    "type": "multiple-choice",
    "question": "Which sentence has the adjective in the correct position?",
    "options": [
      "un rouge chapeau",
      "un chapeau rouge",
      "un chapeau rougement",
      "rougement chapeau un"
    ],
    "answer": "un chapeau rouge",
    "points": 30
  },
  {
    "id": "L3-AD-10",
    "level": 3,
    "topic": "Adjectives",
    "type": "sentence-build",
    "question": "Build: 'I prefer small and quiet restaurants'",
    "words": [
      "Je",
      "préfère",
      "les restaurants",
      "petits",
      "et",
      "calmes"
    ],
    "answer": [
      "Je",
      "préfère",
      "les restaurants",
      "petits",
      "et",
      "calmes"
    ],
    "points": 30
  },
  {
    "id": "L4-PA-01",
    "level": 4,
    "topic": "Past tense",
    "type": "multiple-choice",
    "question": "Which is the correct passé composé of 'parler' for 'je'?",
    "options": [
      "j'ai parlé",
      "j'avais parlé",
      "je parlais",
      "je parlerai"
    ],
    "answer": "j'ai parlé",
    "points": 50
  },
  {
    "id": "L4-PA-02",
    "level": 4,
    "topic": "Past tense",
    "type": "fill-in-blank",
    "question": "Complete: 'Hier, nous ___ au cinéma.' (Yesterday, we went to the cinema.)",
    "options": [
      "sommes allés",
      "allons",
      "irons",
      "allions"
    ],
    "answer": "sommes allés",
    "points": 50
  },
  {
    "id": "L4-PA-03",
    "level": 4,
    "topic": "Past tense",
    "type": "translation",
    "question": "Translate into French: 'She studied for three hours last night'",
    "answer": "Elle a étudié pendant trois heures hier soir",
    "points": 50
  },
  {
    "id": "L4-PA-04",
    "level": 4,
    "topic": "Past tense",
    "type": "multiple-choice",
    "question": "When do you use the imparfait instead of passé composé?",
    "options": [
      "For completed actions",
      "For habitual past actions",
      "For future actions",
      "For conditional actions"
    ],
    "answer": "For habitual past actions",
    "points": 50
  },
  {
    "id": "L4-PA-05",
    "level": 4,
    "topic": "Past tense",
    "type": "sentence-build",
    "question": "Build: 'When I was young, I used to play in the park every day'",
    "words": [
      "Quand",
      "j'étais",
      "jeune,",
      "je jouais",
      "dans le parc",
      "tous les jours"
    ],
    "answer": [
      "Quand",
      "j'étais",
      "jeune,",
      "je jouais",
      "dans le parc",
      "tous les jours"
    ],
    "points": 50
  },
  {
    "id": "L4-PA-06",
    "level": 4,
    "topic": "Past tense",
    "type": "fill-in-blank",
    "question": "Complete: 'Il ___ quand le téléphone a sonné.' (He was sleeping when the phone rang.)",
    "options": [
      "dormait",
      "a dormi",
      "dormira",
      "dormirait"
    ],
    "answer": "dormait",
    "points": 50
  },
  {
    "id": "L4-PA-07",
    "level": 4,
    "topic": "Past tense",
    "type": "translation",
    "question": "Translate into French: 'They had already left when we arrived'",
    "answer": "Ils étaient déjà partis quand nous sommes arrivés",
    "points": 50
  },
  {
    "id": "L4-PA-08",
    "level": 4,
    "topic": "Past tense",
    "type": "multiple-choice",
    "question": "Which verb takes 'être' in the passé composé?",
    "options": [
      "manger",
      "partir",
      "finir",
      "prendre"
    ],
    "answer": "partir",
    "points": 50
  },
  {
    "id": "L4-PA-09",
    "level": 4,
    "topic": "Past tense",
    "type": "sentence-build",
    "question": "Build: 'My parents got married in Paris twenty years ago'",
    "words": [
      "Mes parents",
      "se sont mariés",
      "à Paris",
      "il y a",
      "vingt ans"
    ],
    "answer": [
      "Mes parents",
      "se sont mariés",
      "à Paris",
      "il y a",
      "vingt ans"
    ],
    "points": 50
  },
  {
    "id": "L4-PA-10",
    "level": 4,
    "topic": "Past tense",
    "type": "fill-in-blank",
    "question": "Complete: 'J'avais déjà ___ ce film.' (I had already seen this film.)",
    "options": [
      "vu",
      "voir",
      "voyais",
      "verrai"
    ],
    "answer": "vu",
    "points": 50
  },
  {
    "id": "L4-FU-01",
    "level": 4,
    "topic": "Future tense",
    "type": "multiple-choice",
    "question": "What is the futur simple of 'aller' for 'je'?",
    "options": [
      "je vais",
      "j'irai",
      "j'allais",
      "je suis allé"
    ],
    "answer": "j'irai",
    "points": 50
  },
  {
    "id": "L4-FU-02",
    "level": 4,
    "topic": "Future tense",
    "type": "fill-in-blank",
    "question": "Complete: 'Demain, il ___ du soleil.' (Tomorrow, it will be sunny.)",
    "options": [
      "fera",
      "fait",
      "faisait",
      "ferait"
    ],
    "answer": "fera",
    "points": 50
  },
  {
    "id": "L4-FU-03",
    "level": 4,
    "topic": "Future tense",
    "type": "translation",
    "question": "Translate into French: 'In ten years, I will be a doctor'",
    "answer": "Dans dix ans, je serai médecin",
    "points": 50
  },
  {
    "id": "L4-FU-04",
    "level": 4,
    "topic": "Future tense",
    "type": "sentence-build",
    "question": "Build: 'We will visit France next summer'",
    "words": [
      "Nous",
      "visiterons",
      "la France",
      "l'été prochain"
    ],
    "answer": [
      "Nous",
      "visiterons",
      "la France",
      "l'été prochain"
    ],
    "points": 50
  },
  {
    "id": "L4-FU-05",
    "level": 4,
    "topic": "Future tense",
    "type": "multiple-choice",
    "question": "What is the difference between futur proche and futur simple?",
    "options": [
      "Futur proche is more certain/immediate",
      "Futur simple is more certain/immediate",
      "They are identical",
      "Futur proche is only used in writing"
    ],
    "answer": "Futur proche is more certain/immediate",
    "points": 50
  },
  {
    "id": "L4-FU-06",
    "level": 4,
    "topic": "Future tense",
    "type": "fill-in-blank",
    "question": "Complete: 'Quand tu ___ grand, que veux-tu faire?' (When you grow up, what do you want to do?)",
    "options": [
      "seras",
      "es",
      "étais",
      "serais"
    ],
    "answer": "seras",
    "points": 50
  },
  {
    "id": "L4-FU-07",
    "level": 4,
    "topic": "Future tense",
    "type": "translation",
    "question": "Translate: 'The scientists say the climate will change dramatically'",
    "answer": "Les scientifiques disent que le climat changera de façon dramatique",
    "points": 50
  },
  {
    "id": "L4-FU-08",
    "level": 4,
    "topic": "Future tense",
    "type": "sentence-build",
    "question": "Build: 'If it rains tomorrow, we will stay at home'",
    "words": [
      "S'il",
      "pleut demain,",
      "nous",
      "resterons",
      "à la maison"
    ],
    "answer": [
      "S'il",
      "pleut demain,",
      "nous",
      "resterons",
      "à la maison"
    ],
    "points": 50
  },
  {
    "id": "L4-FU-09",
    "level": 4,
    "topic": "Future tense",
    "type": "multiple-choice",
    "question": "Which is the correct futur simple of 'venir' for 'ils'?",
    "options": [
      "ils viennent",
      "ils venaient",
      "ils viendront",
      "ils sont venus"
    ],
    "answer": "ils viendront",
    "points": 50
  },
  {
    "id": "L4-FU-10",
    "level": 4,
    "topic": "Future tense",
    "type": "fill-in-blank",
    "question": "Complete: 'Elle ___ médecin après ses études.' (She will become a doctor after her studies.)",
    "options": [
      "deviendra",
      "devient",
      "devenait",
      "deviendrait"
    ],
    "answer": "deviendra",
    "points": 50
  },
  {
    "id": "L4-CO-01",
    "level": 4,
    "topic": "Conditional",
    "type": "multiple-choice",
    "question": "What is the conditionnel présent of 'avoir' for 'je'?",
    "options": [
      "j'ai",
      "j'avais",
      "j'aurai",
      "j'aurais"
    ],
    "answer": "j'aurais",
    "points": 50
  },
  {
    "id": "L4-CO-02",
    "level": 4,
    "topic": "Conditional",
    "type": "fill-in-blank",
    "question": "Complete: 'Si j'avais plus d'argent, je ___ une grande maison.' (If I had more money, I would buy a big house.)",
    "options": [
      "achèterais",
      "achète",
      "achèterai",
      "achetais"
    ],
    "answer": "achèterais",
    "points": 50
  },
  {
    "id": "L4-CO-03",
    "level": 4,
    "topic": "Conditional",
    "type": "translation",
    "question": "Translate: 'I would like a coffee please'",
    "answer": "Je voudrais un café s'il vous plaît",
    "points": 50
  },
  {
    "id": "L4-CO-04",
    "level": 4,
    "topic": "Conditional",
    "type": "sentence-build",
    "question": "Build: 'If she studied harder, she would pass her exams'",
    "words": [
      "Si elle",
      "étudiait plus,",
      "elle",
      "réussirait",
      "ses examens"
    ],
    "answer": [
      "Si elle",
      "étudiait plus,",
      "elle",
      "réussirait",
      "ses examens"
    ],
    "points": 50
  },
  {
    "id": "L4-CO-05",
    "level": 4,
    "topic": "Conditional",
    "type": "multiple-choice",
    "question": "Which tense follows 'si' in a conditional sentence (type 2)?",
    "options": [
      "futur simple",
      "conditionnel",
      "imparfait",
      "subjonctif"
    ],
    "answer": "imparfait",
    "points": 50
  },
  {
    "id": "L4-CO-06",
    "level": 4,
    "topic": "Conditional",
    "type": "fill-in-blank",
    "question": "Complete: 'Il ___ venir, mais il était malade.' (He would have come, but he was ill.)",
    "options": [
      "serait venu",
      "viendrait",
      "était venu",
      "viendra"
    ],
    "answer": "serait venu",
    "points": 50
  },
  {
    "id": "L4-CO-07",
    "level": 4,
    "topic": "Conditional",
    "type": "translation",
    "question": "Translate: 'Could you tell me the way to the station?'",
    "answer": "Pourriez-vous m'indiquer le chemin vers la gare?",
    "points": 50
  },
  {
    "id": "L4-CO-08",
    "level": 4,
    "topic": "Conditional",
    "type": "sentence-build",
    "question": "Build: 'In an ideal world, everyone would have access to education'",
    "words": [
      "Dans un monde idéal,",
      "tout le monde",
      "aurait accès",
      "à l'éducation"
    ],
    "answer": [
      "Dans un monde idéal,",
      "tout le monde",
      "aurait accès",
      "à l'éducation"
    ],
    "points": 50
  },
  {
    "id": "L4-CO-09",
    "level": 4,
    "topic": "Conditional",
    "type": "multiple-choice",
    "question": "Which is the polite way to make a request using the conditional?",
    "options": [
      "Donne-moi de l'eau!",
      "Je veux de l'eau.",
      "Pourriez-vous me donner de l'eau?",
      "Donne-moi l'eau s'il te plaît."
    ],
    "answer": "Pourriez-vous me donner de l'eau?",
    "points": 50
  },
  {
    "id": "L4-CO-10",
    "level": 4,
    "topic": "Conditional",
    "type": "fill-in-blank",
    "question": "Complete: 'Si j'avais su, je ne ___ pas venu.' (If I had known, I would not have come.)",
    "options": [
      "serais",
      "suis",
      "serai",
      "sois"
    ],
    "answer": "serais",
    "points": 50
  },
  {
    "id": "L4-FW-01",
    "level": 4,
    "topic": "Formal writing",
    "type": "multiple-choice",
    "question": "Which is the correct formal letter opening?",
    "options": [
      "Salut!",
      "Bonjour,",
      "Madame, Monsieur,",
      "Hey,"
    ],
    "answer": "Madame, Monsieur,",
    "points": 50
  },
  {
    "id": "L4-FW-02",
    "level": 4,
    "topic": "Formal writing",
    "type": "fill-in-blank",
    "question": "Complete the formal closing: 'Veuillez agréer, Madame, Monsieur, l'expression de mes ___ distinguées.'",
    "options": [
      "salutations",
      "amitiés",
      "bises",
      "bonjours"
    ],
    "answer": "salutations",
    "points": 50
  },
  {
    "id": "L4-FW-03",
    "level": 4,
    "topic": "Formal writing",
    "type": "translation",
    "question": "Translate formally: 'I am writing to apply for the position advertised'",
    "answer": "Je me permets de vous écrire afin de postuler au poste annoncé",
    "points": 50
  },
  {
    "id": "L4-FW-04",
    "level": 4,
    "topic": "Formal writing",
    "type": "multiple-choice",
    "question": "Which phrase is appropriate to introduce your purpose in a formal letter?",
    "options": [
      "J'écris parce que...",
      "Je vous écris au sujet de...",
      "Alors voilà...",
      "En gros..."
    ],
    "answer": "Je vous écris au sujet de...",
    "points": 50
  },
  {
    "id": "L4-FW-05",
    "level": 4,
    "topic": "Formal writing",
    "type": "sentence-build",
    "question": "Build a formal phrase: 'I remain at your disposal for any further information'",
    "words": [
      "Je reste",
      "à votre disposition",
      "pour tout",
      "renseignement complémentaire"
    ],
    "answer": [
      "Je reste",
      "à votre disposition",
      "pour tout",
      "renseignement complémentaire"
    ],
    "points": 50
  },
  {
    "id": "L4-FW-06",
    "level": 4,
    "topic": "Formal writing",
    "type": "fill-in-blank",
    "question": "Complete: 'Suite à notre entretien téléphonique, je me permets de vous ___ mon CV.' (Following our telephone conversation, I am pleased to send you my CV.)",
    "options": [
      "faire parvenir",
      "donner",
      "montrer",
      "envoyer"
    ],
    "answer": "faire parvenir",
    "points": 50
  },
  {
    "id": "L4-FW-07",
    "level": 4,
    "topic": "Formal writing",
    "type": "multiple-choice",
    "question": "Which is NOT appropriate in formal French writing?",
    "options": [
      "Par conséquent",
      "En outre",
      "C'est trop cool",
      "Néanmoins"
    ],
    "answer": "C'est trop cool",
    "points": 50
  },
  {
    "id": "L4-FW-08",
    "level": 4,
    "topic": "Formal writing",
    "type": "translation",
    "question": "Translate: 'We apologise for any inconvenience caused'",
    "answer": "Nous vous prions de bien vouloir nous excuser pour la gêne occasionnée",
    "points": 50
  },
  {
    "id": "L4-FW-09",
    "level": 4,
    "topic": "Formal writing",
    "type": "fill-in-blank",
    "question": "Complete: '___ à votre réponse, je vous prie d'agréer...' (Awaiting your reply...)",
    "options": [
      "Dans l'attente",
      "En attendant",
      "Espérant",
      "Comptant sur"
    ],
    "answer": "Dans l'attente",
    "points": 50
  },
  {
    "id": "L4-FW-10",
    "level": 4,
    "topic": "Formal writing",
    "type": "multiple-choice",
    "question": "Which connector is best for showing contrast in formal writing?",
    "options": [
      "mais",
      "et",
      "toutefois",
      "parce que"
    ],
    "answer": "toutefois",
    "points": 50
  },
  {
    "id": "L4-ID-01",
    "level": 4,
    "topic": "Idioms",
    "type": "multiple-choice",
    "question": "What does 'Casser les pieds de quelqu'un' mean?",
    "options": [
      "To kick someone",
      "To annoy someone",
      "To help someone walk",
      "To follow someone"
    ],
    "answer": "To annoy someone",
    "points": 50
  },
  {
    "id": "L4-ID-02",
    "level": 4,
    "topic": "Idioms",
    "type": "multiple-choice",
    "question": "What does 'Il pleut des cordes' mean literally used as an idiom?",
    "options": [
      "It is raining cats and dogs",
      "It is sunny",
      "The ropes are wet",
      "It rains every day"
    ],
    "answer": "It is raining cats and dogs",
    "points": 50
  },
  {
    "id": "L4-ID-03",
    "level": 4,
    "topic": "Idioms",
    "type": "fill-in-blank",
    "question": "Complete the idiom: 'Avoir le ___ vide.' = To be starving (To have an empty stomach)",
    "options": [
      "ventre",
      "coeur",
      "tête",
      "poche"
    ],
    "answer": "ventre",
    "points": 50
  },
  {
    "id": "L4-ID-04",
    "level": 4,
    "topic": "Idioms",
    "type": "translation",
    "question": "Translate the idiom into English: 'Poser un lapin à quelqu'un'",
    "answer": "To stand someone up",
    "points": 50
  },
  {
    "id": "L4-ID-05",
    "level": 4,
    "topic": "Idioms",
    "type": "multiple-choice",
    "question": "What does 'Avoir le cafard' mean?",
    "options": [
      "To be very happy",
      "To feel down/depressed",
      "To be very busy",
      "To be confused"
    ],
    "answer": "To feel down/depressed",
    "points": 50
  },
  {
    "id": "L4-ID-06",
    "level": 4,
    "topic": "Idioms",
    "type": "fill-in-blank",
    "question": "Complete: 'Ce n'est pas la ___ à couper le beurre.' (It's not rocket science.)",
    "options": [
      "mer",
      "rue",
      "montagne",
      "forêt"
    ],
    "answer": "mer",
    "points": 50
  },
  {
    "id": "L4-ID-07",
    "level": 4,
    "topic": "Idioms",
    "type": "multiple-choice",
    "question": "What does 'Avoir d'autres chats à fouetter' mean?",
    "options": [
      "To have many cats",
      "To have more important things to do",
      "To be very angry",
      "To be very busy with animals"
    ],
    "answer": "To have more important things to do",
    "points": 50
  },
  {
    "id": "L4-ID-08",
    "level": 4,
    "topic": "Idioms",
    "type": "translation",
    "question": "Translate into French: 'To hit the nail on the head'",
    "answer": "Mettre le doigt dessus",
    "points": 50
  },
  {
    "id": "L4-ID-09",
    "level": 4,
    "topic": "Idioms",
    "type": "multiple-choice",
    "question": "What does 'Revenons à nos moutons' mean?",
    "options": [
      "Let's go to the farm",
      "Let's get back to the subject",
      "Let's count sheep",
      "Let's start again"
    ],
    "answer": "Let's get back to the subject",
    "points": 50
  },
  {
    "id": "L4-ID-10",
    "level": 4,
    "topic": "Idioms",
    "type": "fill-in-blank",
    "question": "Complete: 'Coûter les ___ et la terre.' (To cost an arm and a leg.)",
    "options": [
      "yeux",
      "dents",
      "bras",
      "oreilles"
    ],
    "answer": "yeux",
    "points": 50
  },
  {
    "id": "L4-RC-01",
    "level": 4,
    "topic": "Reading comprehension",
    "type": "multiple-choice",
    "question": "Read: 'Marie est allée au marché ce matin. Elle a acheté des légumes frais et du pain.' What did Marie buy?",
    "options": [
      "Fruit and cheese",
      "Vegetables and bread",
      "Meat and fish",
      "Milk and eggs"
    ],
    "answer": "Vegetables and bread",
    "points": 50
  },
  {
    "id": "L4-RC-02",
    "level": 4,
    "topic": "Reading comprehension",
    "type": "fill-in-blank",
    "question": "Read: 'Bien que le temps soit mauvais, nous avons décidé de partir en randonnée.' The word 'Bien que' means:",
    "options": [
      "Although",
      "Because",
      "Therefore",
      "However"
    ],
    "answer": "Although",
    "points": 50
  },
  {
    "id": "L4-RC-03",
    "level": 4,
    "topic": "Reading comprehension",
    "type": "multiple-choice",
    "question": "Read: 'La France est le pays le plus visité au monde, accueillant plus de 80 millions de touristes par an.' What fact is stated?",
    "options": [
      "France is in Europe",
      "France has 80 million inhabitants",
      "France is the most visited country",
      "France has 80 national parks"
    ],
    "answer": "France is the most visited country",
    "points": 50
  },
  {
    "id": "L4-RC-04",
    "level": 4,
    "topic": "Reading comprehension",
    "type": "translation",
    "question": "Translate this paragraph: 'La pollution de l'air dans les grandes villes est un problème majeur qui affecte la santé de millions de personnes.'",
    "answer": "Air pollution in large cities is a major problem that affects the health of millions of people.",
    "points": 50
  },
  {
    "id": "L4-RC-05",
    "level": 4,
    "topic": "Reading comprehension",
    "type": "multiple-choice",
    "question": "Read: 'Contrairement à ce qu'on pourrait croire, les pieuvres sont des animaux très intelligents.' What does this say about octopuses?",
    "options": [
      "They are dangerous",
      "They are surprisingly intelligent",
      "They are not intelligent",
      "They are easy to catch"
    ],
    "answer": "They are surprisingly intelligent",
    "points": 50
  },
  {
    "id": "L4-RC-06",
    "level": 4,
    "topic": "Reading comprehension",
    "type": "fill-in-blank",
    "question": "Read: 'D'une part, les réseaux sociaux facilitent la communication. D'autre part, ils peuvent créer de l'isolement.' The text structure shows:",
    "options": [
      "two contrasting points",
      "cause and effect",
      "a timeline",
      "a list"
    ],
    "answer": "two contrasting points",
    "points": 50
  },
  {
    "id": "L4-RC-07",
    "level": 4,
    "topic": "Reading comprehension",
    "type": "multiple-choice",
    "question": "Read: 'Il convient de souligner que cette décision a été prise à l'unanimité.' What does 'à l'unanimité' mean?",
    "options": [
      "With some disagreement",
      "By one person",
      "Unanimously",
      "After a long debate"
    ],
    "answer": "Unanimously",
    "points": 50
  },
  {
    "id": "L4-RC-08",
    "level": 4,
    "topic": "Reading comprehension",
    "type": "translation",
    "question": "Translate: 'Les chercheurs ont découvert que dormir suffisamment améliore considérablement les capacités cognitives.'",
    "answer": "Researchers have discovered that sleeping enough considerably improves cognitive abilities.",
    "points": 50
  },
  {
    "id": "L4-RC-09",
    "level": 4,
    "topic": "Reading comprehension",
    "type": "sentence-build",
    "question": "Summarise in French: 'Climate change is the biggest challenge of our century'",
    "words": [
      "Le changement climatique",
      "est",
      "le plus grand défi",
      "de notre siècle"
    ],
    "answer": [
      "Le changement climatique",
      "est",
      "le plus grand défi",
      "de notre siècle"
    ],
    "points": 50
  },
  {
    "id": "L4-RC-10",
    "level": 4,
    "topic": "Reading comprehension",
    "type": "multiple-choice",
    "question": "Read: 'Non seulement il parle français couramment, mais il maîtrise également l'espagnol et le mandarin.' How many languages does he speak?",
    "options": [
      "One",
      "Two",
      "Three",
      "Four"
    ],
    "answer": "Three",
    "points": 50
  }
]